EasyDrive/Drives.py
EasyDrive/Exceptions.py
EasyDrive/FileSystemTypes.py
EasyDrive/MIMETypes.py
EasyDrive/__init__.py
EasyDrive-0.0.8.dist-info/METADATA
EasyDrive-0.0.8.dist-info/WHEEL
EasyDrive-0.0.8.dist-info/top_level.txt
EasyDrive-0.0.8.dist-info/RECORD
