Metadata-Version: 2.1
Name: EasyDrive
Version: 0.0.8
Summary: EasyGoogle Drive access
Author-email: RanchMonster <ranchmonster06@outlook.com>
Classifier: Programming Language :: Python :: 3
Classifier: License :: OSI Approved :: MIT License
Classifier: Operating System :: OS Independent
Requires-Python: >3.8
Requires-Dist: google-api-python-client
Requires-Dist: google-auth-httplib2
